[
  {
    "id": "drivers",
    "title": "Drivers",
    "description": "All the endpoints related to the drivers.",
    "url": "drivers",
    "section": "drivers",
    "endpoints": [
      {
        "id": "drivers",
        "title": "drivers",
        "description": "This endpoint retrieves details about a all the drivers in the database. The active and the old drivers.",
        "url": "drivers",
        "params": [
          {
            "name": "limit",
            "description": "Number of records returned per request.",
            "default": "30"
          },
          {
            "name": "offset",
            "description": "Number of records skipped before starting to fetch.",
            "default": "0"
          }
        ]
      },
      {
        "id": "driverId",
        "title": "[driverId]",
        "description": "This endpoint retrieves details about a driver in the database. Based on the provided driverId.",
        "url": "driverId"
      }
    ]
  },
  {
    "id": "teams",
    "title": "Teams",
    "description": "All the endpoints related to the teams.",
    "url": "teams",
    "section": "teams",
    "endpoints": [
      {
        "id": "teams",
        "title": "teams",
        "description": "This endpoint retrieves details about a all the teams in the database. The active and the old teams.",
        "url": "teams",
        "params": "limit=1&offset=20"
      },
      {
        "id": "teamId",
        "title": "[teamId]",
        "description": "This endpoint retrieves details about a team in the database. Based on the provided teamId.",
        "url": "teamId"
      }
    ]
  },
  {
    "id": "seasons",
    "title": "Seasons",
    "description": "This endpoint retrieves details about a all the drivers in the database. The active and the old drivers.",
    "url": "seasons",
    "section": "seasons",
    "endpoints": [
      {
        "id": "seasons",
        "title": "Seasons",
        "description": "This endpoint retrieves details about a all the drivers in the database. The active and the old drivers.",
        "url": "seasons",
        "params": "limit=1&offset=20"
      },
      {
        "id": "seasonId",
        "title": "Season per Id",
        "description": "This endpoint retrieves details about a all the drivers in the database. The active and the old drivers.",
        "url": "driverId"
      }
    ]
  },
  {
    "id": "races",
    "title": "Races",
    "description": "This endpoint retrieves details about a all the drivers in the database. The active and the old drivers.",
    "url": "races",
    "section": "races",
    "endpoints": [
      {
        "id": "races",
        "title": "Races",
        "description": "This endpoint retrieves details about a all the drivers in the database. The active and the old drivers.",
        "url": "races",
        "params": "limit=1&offset=20"
      },
      {
        "id": "raceId",
        "title": "Race per Id",
        "description": "This endpoint retrieves details about a all the drivers in the database. The active and the old drivers.",
        "url": "driverId"
      }
    ]
  },
  {
    "id": "standings",
    "title": "Standings",
    "description": "This endpoint retrieves details about a all the drivers in the database. The active and the old drivers.",
    "url": "standings",
    "section": "standings",
    "endpoints": [
      {
        "id": "standings",
        "title": "Standings",
        "description": "This endpoint retrieves details about a all the drivers in the database. The active and the old drivers.",
        "url": "standings",
        "params": "limit=1&offset=20"
      },
      {
        "id": "standingsId",
        "title": "Standings per Id",
        "description": "This endpoint retrieves details about a all the drivers in the database. The active and the old drivers.",
        "url": "driverId"
      }
    ]
  },
  {
    "id": "circuits",
    "title": "Circuits",
    "description": "This endpoint retrieves details about a all the circuits in the database. The active and the old.",
    "url": "circuits",
    "section": "circuits",
    "endpoints": [
      {
        "id": "circuits",
        "title": "Circuits",
        "description": "This endpoint retrieves details about a all the circuits in the database. The active and the old circuits.",
        "url": "circuits",
        "params": "limit=1&offset=20"
      },
      {
        "id": "circuitId",
        "title": "[circuitId]",
        "description": "This endpoint retrieves details about circuits in the database with the given Id.",
        "url": "circuitId"
      }
    ]
  }
]
